sanic_mongo/__init__.py
sanic_mongo/gridfs.py
sanic_mongo/mongo.py
sanic_mongo/standalone/__init__.py
sanic_mongo/standalone/mongo_GridFs.py
sanic_mongo/standalone/mongo_connection.py
sanic_mongo-1.7.1.data/data/requirements/requirements.txt
sanic_mongo-1.7.1.dist-info/DESCRIPTION.rst
sanic_mongo-1.7.1.dist-info/METADATA
sanic_mongo-1.7.1.dist-info/RECORD
sanic_mongo-1.7.1.dist-info/WHEEL
sanic_mongo-1.7.1.dist-info/metadata.json
sanic_mongo-1.7.1.dist-info/top_level.txt
